sphractal/__init__.py
sphractal/boxCnt.py
sphractal/constants.py
sphractal/data/__init__.py
sphractal/data/caseStudyOTS1T000.xyz
sphractal/data/caseStudyOTS1T323.xyz
sphractal/data/caseStudyOTS1T523.xyz
sphractal/data/caseStudyOTS2T000.xyz
sphractal/data/caseStudyOTS2T323.xyz
sphractal/data/caseStudyOTS2T523.xyz
sphractal/data/caseStudyRDS1T000.xyz
sphractal/data/caseStudyRDS1T323.xyz
sphractal/data/caseStudyRDS1T523.xyz
sphractal/data/caseStudyRDS2T000.xyz
sphractal/data/caseStudyRDS2T323.xyz
sphractal/data/caseStudyRDS2T523.xyz
sphractal/data/caseStudyTHS1T000.xyz
sphractal/data/caseStudyTHS1T323.xyz
sphractal/data/caseStudyTHS1T523.xyz
sphractal/data/caseStudyTHS2T000.xyz
sphractal/data/caseStudyTHS2T323.xyz
sphractal/data/caseStudyTHS2T523.xyz
sphractal/data/dna.xyz
sphractal/data/exampleOT.xyz
sphractal/data/graphene.xyz
sphractal/data/paracetamol.xyz
sphractal/data/singleAtom.xyz
sphractal/data/strongScalingSP.xyz
sphractal/data/weakScalingSP00.xyz
sphractal/data/weakScalingSP01.xyz
sphractal/data/weakScalingSP02.xyz
sphractal/data/weakScalingSP03.xyz
sphractal/data/weakScalingSP04.xyz
sphractal/data/weakScalingSP05.xyz
sphractal/data/weakScalingSP06.xyz
sphractal/data/weakScalingSP07.xyz
sphractal/data/weakScalingSP08.xyz
sphractal/data/weakScalingSP09.xyz
sphractal/data/weakScalingSP10.xyz
sphractal/data/weakScalingSP11.xyz
sphractal/datasets.py
sphractal/surfExact.py
sphractal/surfVoxel.py
sphractal/utils.py
sphractal-1.1.17.dist-info/LICENSE
sphractal-1.1.17.dist-info/METADATA
sphractal-1.1.17.dist-info/WHEEL
sphractal-1.1.17.dist-info/RECORD
