Metadata-Version: 2.3
Name: sphractal
Version: 1.1.17
Summary: Package to estimate fractal dimension of 3D surfaces formed from overlapping spheres via box-counting algorithm.
License: MIT
Keywords: box-counting,box-count,fractal,dimension,sphere,surface
Author: Jonathan Yik Chang Ting
Author-email: jonting97@gmail.com
Requires-Python: >=3.9
Classifier: Intended Audience :: Science/Research
Classifier: License :: OSI Approved :: MIT License
Classifier: Natural Language :: English
Classifier: Operating System :: OS Independent
Classifier: Programming Language :: C++
Classifier: Programming Language :: Python :: 3
Classifier: Programming Language :: Python :: 3.9
Classifier: Programming Language :: Python :: 3.10
Classifier: Programming Language :: Python :: 3.11
Classifier: Programming Language :: Python :: 3.12
Classifier: Programming Language :: Python :: 3.13
Classifier: Topic :: Scientific/Engineering
Requires-Dist: matplotlib (>=3.7.1)
Requires-Dist: numba (>=0.57.1)
Requires-Dist: numpy (>=1.22,<1.25)
Requires-Dist: scipy (>=1.11.1) ; python_version >= "3.9" and python_version < "3.13"
Requires-Dist: statsmodels (>=0.14.0)
Project-URL: Documentation, https://sphractal.readthedocs.io/en/latest/
Project-URL: Homepage, https://github.com/Jon-Ting/sphractal
Project-URL: Repository, https://github.com/Jon-Ting/sphractal
